sqlite3paramstyle/__init__.py
sqlite3paramstyle/connection.py
sqlite3paramstyle-0.0.2.dist-info/DESCRIPTION.rst
sqlite3paramstyle-0.0.2.dist-info/METADATA
sqlite3paramstyle-0.0.2.dist-info/metadata.json
sqlite3paramstyle-0.0.2.dist-info/RECORD
sqlite3paramstyle-0.0.2.dist-info/top_level.txt
sqlite3paramstyle-0.0.2.dist-info/WHEEL
