Metadata-Version: 2.0
Name: sqlite3paramstyle
Version: 0.0.2
Summary: Extended paramstyle for sqlite3 module
Home-page: https://github.com/shrkw/sqlite3_paramstyle
Author: Hiroyuki Shirakawa
Author-email: shrkwh@gmail.com
License: MIT License
Keywords: sqlite,sqlite3
Platform: UNKNOWN
Classifier: Development Status :: 4 - Beta
Classifier: License :: OSI Approved :: MIT License
Classifier: Programming Language :: Python :: 2.7
Classifier: Programming Language :: Python :: 3.4
Classifier: Topic :: Database
